[
    {
        "firstName": "John",
        "lastName": "Doe",
        "username": "jdoe",
        "password": "welcome123",
        "email": "jdoe@gmail.com"
    },
    {
        "firstName": "Lance",
        "lastName": "Anozie",
        "username": "lanozie",
        "password": "welcome123",
        "email": "lanozie@hotmail.com"
    },
    {
        "firstName": "Jane",
        "lastName": "Doe",
        "username": "jdoe01",
        "password": "welcome123",
        "email": "jdoe02@microsoft.com"
    }
]