[
    {
        "id": 1,
        "name": "First Aid Kit (216 Pieces)",
        "description": "A comprehensive first aid kit containing 216 essential items for emergency situations.",
        "image": "../images/americanredcross_firstaidkit.jpg",
        "price": 34.99,
      "quantity": 10,
      "category": "First Aid",
      "isRentable": false,
      "rentalPrice": 1.99,
      "rentalPeriod": 7,
      "rentalStock": 10
    },
    {
      "id": 2,
      "name": "Mask",
      "description": "50 Pcs Disposable 4-ply Non-Woven Face Mask",
      "image": "../images/blackmask.jpg",
      "price": 5.99,
      "quantity": 10,
      "category": "PPE",
      "isRentable": false,
      "rentalPrice": 1.99,
      "rentalPeriod": 7,
      "rentalStock": 10
    },
    {
        "id": 3,
        "name": "Blood Pressure Monitor",
        "description": "Blood Pressure Monitor for Upper Arm Large w/LED Screen",
        "image": "../images/bloodpressure_monitor.jpg",
        "price": 45.99,
        "quantity": 10,
        "category": "Devices",
        "isRentable": true,
        "rentalPrice": 1.99,
        "rentalPeriod": 7,
        "rentalStock": 10
      },
      {
        "id": 4,
        "name": "BlueTooth Blood Pressure Monitor",
        "description": "Bluetooth Blood Pressure Monitors for Home Use",
        "image": "../images/bluetoothbloodpressure.jpg",
        "price": 65.99,
        "quantity": 10,
        "category": "Devices",
        "isRentable": true,
        "rentalPrice": 1.99,
        "rentalPeriod": 7,
        "rentalStock": 10
      },
      {
        "id": 5,
        "name": "Pregnancy Test",
        "description": "Can tell you results 6 days sooner than your missed period",
        "image": "../images/clearbluepregotest.jpg",
        "price": 12.99,
        "quantity": 40,
        "category": "Tests",
        "isRentable": false,
        "rentalPrice": 1.99,
        "rentalPeriod": 7,
        "rentalStock": 10
      },
      {
        "id": 6,
        "name": "Dual Head Stethoscope",
        "description": "This is product 2",
        "image": "../images/dualheadstethoscope.jpg",
        "price": 15.99,
        "quantity": 10,
        "category": "Devices",
        "isRentable": true,
        "rentalPrice": 1.99,
        "rentalPeriod": 7,
        "rentalStock": 10
      },
      {
        "id": 7,
        "name": "First Aid Kit (193 Pieces)",
        "description": "Milwaukee PACKOUT Class B Type III First Aid Kit",
        "image": "../images/firstaidkit_milwa.png",
        "price": 5.99,
        "quantity": 10,
        "category": "First Aid",
        "isRentable": false,
        "rentalPrice": 6.99,
        "rentalPeriod": 7,
        "rentalStock": 10
      },
      {
            "id": 8,
            "name": "Force Mech Electric Wheelchair",
            "description": "A versatile and comfortable electric wheelchair designed for easy mobility.",
            "image": "../images/forcemech.jpg",
            "price": 1799.00,
            "quantity": 10,
            "category": "Wheelchairs",
            "isRentable": true,
            "rentalPrice": 99.00,
            "rentalPeriod": 7,
            "rentalStock": 10
        },
        {
            "id": 9,
            "name": "MDF Stethoscope",
            "description": "A professional-grade stethoscope with excellent acoustic performance.",
            "image": "../images/mdf_stethoscope.jpg",
            "price": 49.99,
            "quantity": 10,
            "category": "Devices",
            "isRentable": true,
            "rentalPrice": 9.99,
            "rentalPeriod": 7,
            "rentalStock": 10
        },
        {
            "id": 10,
            "name": "Multifunctional Children's Wheelchair",
            "description": "An adjustable and ergonomic wheelchair designed specifically for children.",
            "image": "../images/multifunctionalchildrenschair.jpg",
            "price": 599.00,
            "quantity": 10,
            "category": "Wheelchairs",
            "isRentable": true,
            "rentalPrice": 49.00,
            "rentalPeriod": 7,
            "rentalStock": 10
        },
        {
            "id": 11,
            "name": "Tenice Multi-Color Masks",
            "description": "A pack of multi-colored, comfortable masks for personal protection.",
            "image": "../images/tenicemasks.jpg",
            "price": 14.99,
            "quantity": 10,
            "category": "PPE",
            "isRentable": false,
            "rentalPrice": 4.99,
            "rentalPeriod": 7,
            "rentalStock": 10
        },
        {
            "id": 12,
            "name": "Ultra-lightweight Wheelchair",
            "description": "A lightweight wheelchair designed for ease of use and maneuverability.",
            "image": "../images/ultralightwheelchair.jpg",
            "price": 699.00,
            "quantity": 10,
            "category": "Wheelchairs",
            "isRentable": true,
            "rentalPrice": 29.99,
            "rentalPeriod": 7,
            "rentalStock": 10
        },
      {
        "id": 13,
        "name": "Binax COVID test",
        "description": "Antigen self test",
        "image": "../images/binaxcovidtest.jpg",
        "price": 24.99,
        "quantity": 10,
        "category": "Tests",
        "isRentable": false,
        "rentalPrice": 1.99,
        "rentalPeriod": 7,
        "rentalStock": 10
      },
      {
        "id": 14,
        "name": "Bose Hearing Aids",
        "description": "Bose Hearing Aids",
        "image": "../images/bosshearingaids.jpg",
        "price": 895.99,
        "quantity": 10,
        "category": "Devices",
        "isRentable": false,
        "rentalPrice": 1.99,
        "rentalPeriod": 7,
        "rentalStock": 10
      },
      {
        "id": 15,
        "name": "UV Light Sanitizer",
        "description": "Disinfect anywhere your vehicle, sofa, phone, and more",
        "image": "../images/uvsanitizerlamp.jpg",
        "price": 35.99,
        "quantity": 15,
        "category": "Devices",
        "isRentable": true,
        "rentalPrice": 1.99,
        "rentalPeriod": 7,
        "rentalStock": 5
      },
      {
        "id": 16,
        "name": "Baby bottle UV Sterilizer",
        "description": "You can sterilize your baby's bottle with this",
        "image": "../images/uvsterilizerbabybottles.jpg",
        "price": 125.99,
        "quantity": 10,
        "category": "Devices",
        "isRentable": true,
        "rentalPrice": 20.99,
        "rentalPeriod": 7,
        "rentalStock": 10
      },
      {
        "id": 17,
        "name": "Strength Training for Seniors Book",
        "description": "For that old man grip",
        "image": "../images/seniorstrengthbook.jpg",
        "price": 15.99,
        "quantity": 10,
        "category": "Books",
        "isRentable": false,
        "rentalPrice": 1.99,
        "rentalPeriod": 7,
        "rentalStock": 10
      },
      {
        "id": 18,
        "name": "Everly Well test Kit",
        "description": "A test kit for allergens and intolerances",
        "image": "../images/sharktankeverlywell.jpg",
        "price": 5.99,
        "quantity": 10,
        "category": "Tests",
        "isRentable": false,
        "rentalPrice": 1.99,
        "rentalPeriod": 7,
        "rentalStock": 10
      },
      {
        "id": 19,
        "name": "UV-C Disinfection Robot",
        "description": "Fast, efficient, and chemical free UV solution guaranteeing a whole-room disinfection.",
        "image": "../images/ultralightwheelchair.jpg",
        "price": 1499.99,
        "quantity": 8,
        "category": "Devices",
        "isRentable": true,
        "rentalPrice": 149.99,
        "rentalPeriod": 7,
        "rentalStock": 8
      },
      {
        "id": 20,
        "name": "EVERLIT Advanced Emergency Trauma Kit",
        "description": "Military Combat Tactical IFAK for First Aid Response Bleeding Control",
        "image": "../images/advemergencytrauma.jpg",
        "price": 115.99,
        "quantity": 5,
        "category": "First Aid",
        "isRentable": false,
        "rentalPrice": 1.99,
        "rentalPeriod": 7,
        "rentalStock": 10
      },
      {
        "id": 21,
        "name": "Watch Pill ",
        "description": "The pill box size is 1.38 inch (diameter)*0.3 inch (Height) Pill container locks and opens with a secure and simple button so it won't pop open and spill.",
        "image": "../images/watchpillbox.jpg",
        "price": 5.99,
        "quantity": 10,
        "category": "Devices",
        "isRentable": false,
        "rentalPrice": 1.99,
        "rentalPeriod": 7,
        "rentalStock": 10
      },
      {
        "id": 22,
        "name": "HiccAway straw",
        "description": "The only drug free, reusable natural cure for hiccups is available in Single Packs",
        "image": "../images/sharktankhicc.jpg",
        "price": 11.99,
        "quantity": 20,
        "category": "Devices",
        "isRentable": false,
        "rentalPrice": 1.99,
        "rentalPeriod": 7,
        "rentalStock": 10
    },
    {
      "id": 23,
      "name": "Ava Elephant",
      "description": "Ava helps administer the entire medicine dosage on the first try and it creates a pleasant experience for kids to take their medicines and gives them positive reinforcement.",
      "image": "../images/sharktankavaelephant.jpg",
      "price": 9.99,
      "quantity": 25,
      "category": "Devices",
      "isRentable": false,
      "rentalPrice": 1.99,
      "rentalPeriod": 7,
      "rentalStock": 10
    },
    {
      "id": 24,
      "name": "Lepulse Smart Weight Scale",
      "description": "15 Essential Body Composition Analyzer with LED screen.",
      "image": "../images/smartweightscale.jpg",
      "price": 49.99,
      "quantity": 7,
      "category": "Devices",
      "isRentable": false,
      "rentalPrice": 1.99,
      "rentalPeriod": 7,
      "rentalStock": 10
    },
    {
      "id": 25,
      "name": "Health O Meter Digital Medical Scale",
      "description": "High 500 lb./ 220 kg capacity with professional grade accuracy",
      "image": "../images/healthometerscale.jpg",
      "price": 349.99,
      "quantity": 3,
      "category": "Devices",
      "isRentable": true,
      "rentalPrice": 54.99,
      "rentalPeriod": 7,
      "rentalStock": 2
    }
  ]